qatarcars/__init__.py
qatarcars/_errors.py
qatarcars/_utils.py
qatarcars/cars.py
qatarcars/data/__init__.py
qatarcars/data/qatarcars.csv
qatarcars-0.2.0.dist-info/LICENSE
qatarcars-0.2.0.dist-info/METADATA
qatarcars-0.2.0.dist-info/WHEEL
qatarcars-0.2.0.dist-info/RECORD
