Metadata-Version: 2.3
Name: qatarcars
Version: 0.2.0
Summary: A package containing data on Qatari cars for pedagogical purposes
License: CC0 v1.0 Universal
Author: Peter Licari
Requires-Python: >=3.9
Classifier: License :: Other/Proprietary License
Classifier: Programming Language :: Python :: 3
Classifier: Programming Language :: Python :: 3.9
Classifier: Programming Language :: Python :: 3.10
Classifier: Programming Language :: Python :: 3.11
Classifier: Programming Language :: Python :: 3.12
Classifier: Programming Language :: Python :: 3.13
Requires-Dist: colorama (==0.4.6)
